<configuration>
  <property>
    <name>fs.defaultFS</name>
    <value>hdfs://localhost:54310</value>
  </property>
  <property>
    <name>fs.trash.interval</name>
    <value>30</value>
    <description>Number of minutes between trash checkpoints</description>
  </property>
  <property>
    <name>fs.trash.checkpoint.interval</name>
    <value>15</value>
  </property>
  <property>
    <name>fs.s3a.access.key</name>
    <value>YOUR_AWS_ACCESS_KEY</value>
  </property>
  <property>
    <name>fs.s3a.secret.key</name>
    <value>YOUR_AWS_SECRET_KEY</value>
  </property>
  <property>
    <name>fs.s3.impl</name>
    <value>org.apache.hadoop.fs.s3.S3FileSystem</value>
  </property>
</configuration>
